{"characterInfos":[
{"id":"champion_001", "keyName":"Gunslinger", "speed":100, "hp":1, "maxHp":1, "lv":1, "image":"Gunslinger", "weaponId":"null"}, 
{"id":"champion_002", "keyName":"Buster", "speed":100, "hp":1, "maxHp":1, "lv":1, "image":"Buster", "weaponId":"null"},
{"id":"champion_003", "keyName":"CannonShooter", "speed":100, "hp":1, "maxHp":1, "lv":1, "image":"CannonShooter", "weaponId":"null"},
{"id":"monster_001", "keyName":"unName1", "speed":100, "hp":1, "maxHp":1, "lv":1, "image":"CannonShooter", "weaponId":"null"}
]}